mailtorpedo/__init__.py
mailtorpedo/binder.py
mailtorpedo/reader.py
mailtorpedo/sender.py
mailtorpedo/template.py
mailtorpedo/utils.py
mailtorpedo/tests/__init__.py
mailtorpedo/tests/__main__.py
mailtorpedo/tests/binder.py
mailtorpedo/tests/data_checks.py
mailtorpedo/tests/reader.py
mailtorpedo/tests/template.py
mailtorpedo/tests/utils.py
mailtorpedo-1.1.0.dist-info/LICENSE
mailtorpedo-1.1.0.dist-info/METADATA
mailtorpedo-1.1.0.dist-info/WHEEL
mailtorpedo-1.1.0.dist-info/top_level.txt
mailtorpedo-1.1.0.dist-info/RECORD
