Metadata-Version: 2.1
Name: mailtorpedo
Version: 1.1.0
Summary: A Python package for sending personalized emails using own SMTP server.
Home-page: https://github.com/pptx704/torpedo
Author: Rafeed M. Bhuiyan
Author-email: rafeedm.bhuiyan@gmail.com
License: UNKNOWN
Project-URL: Bug Tracker, https://github.com/pptx704/torpedo/issues
Platform: UNKNOWN
Classifier: Programming Language :: Python :: 3
Classifier: License :: OSI Approved :: MIT License
Classifier: Operating System :: OS Independent
Requires-Python: >=3.6
License-File: LICENSE
Requires-Dist: beautifulsoup4
Requires-Dist: openpyxl
